HISTORY.txt
LICENSE.txt
MANIFEST.in
README.rst
cx_setup.py
hello_world.py
setup.py
docs/Makefile
docs/api.rst
docs/conf.py
docs/example.py
docs/example_tables.py
docs/gettingstarted.rst
docs/index.rst
docs/make.bat
docs/usage.rst
docs/_static/.empty
docs/_templates/.empty
examples/__init__.py
examples/cable_list_from_schemes.py
examples/cable_tables_to_csv.py
examples/cables_xls_to_autocad.py
examples/calc_cb_place_consumption.py
examples/dev_get_table_info.py
examples/get_names.py
examples/lights.py
pyzwcad/__init__.py
pyzwcad/api.py
pyzwcad/cache.py
pyzwcad/compat.py
pyzwcad/types.py
pyzwcad/utils.py
pyzwcad.egg-info/PKG-INFO
pyzwcad.egg-info/SOURCES.txt
pyzwcad.egg-info/dependency_links.txt
pyzwcad.egg-info/requires.txt
pyzwcad.egg-info/top_level.txt
pyzwcad/contrib/__init__.py
pyzwcad/contrib/tables.py
tests/__init__.py
tests/test_api.py
tests/test_api_a.py
tests/test_cached.py
tests/test_cached_a.py
tests/test_contrib_tables.py
tests/test_contrib_tables_a.py
tests/test_some_ideas.py
tests/test_some_ideas_a.py
tests/test_types.py
tests/test_types_a.py
tests/test_utils.py
tests/test_utils_a.py